{
	"name": "MenuButton",
	"plugin-id": "Sprite",
	"sid": 505946989591839,
	"isGlobal": false,
	"instanceVariables": [],
	"behaviorTypes": [],
	"effectTypes": [],
	"animations": {
		"items": [
			{
				"frames": [
					{
						"width": 112,
						"height": 48,
						"originX": 0,
						"originY": 0,
						"originalSource": "",
						"exportFormat": "png",
						"exportQuality": 0.8,
						"imageSpriteId": 3047123,
						"collisionPoly": {
							"points": [
								0.11986863711001643,
								0.27756653992395436,
								0.5,
								0.41825095057034223,
								0.7651888341543513,
								0.5399239543726235,
								0.8784893267651889,
								0.5,
								0.8768472906403941,
								0.714828897338403,
								0.5,
								0.7224334600760456,
								0.11658456486042693,
								0.7262357414448669,
								0.11822660098522167,
								0.5
							]
						},
						"useCollisionPoly": true,
						"duration": 1
					}
				],
				"sid": 178010592445372,
				"name": "Animation 1",
				"isLooping": false,
				"isPingPong": false,
				"repeatCount": 1,
				"repeatTo": 0,
				"speed": 5
			}
		],
		"subfolders": []
	}
}