{
	"name": "Objects",
	"layers": [
		{
			"name": "Layer 0",
			"overriden": 0,
			"instances": [
				{
					"type": "Waypoint",
					"properties": {
						"initially-visible": true,
						"initial-animation": "Animation 1",
						"initial-frame": 0,
						"enable-collisions": true,
						"live-preview": false
					},
					"uid": 2,
					"instanceVariables": {
						"Index": 0
					},
					"behaviors": {},
					"world": {
						"x": 321.48211868207454,
						"y": 114.48211868207454,
						"width": 155.88861027839778,
						"height": 155.88861027839778,
						"originX": 0.5,
						"originY": 0.5,
						"color": [
							1,
							1,
							1,
							1
						],
						"angle": 0,
						"zElevation": 0
					}
				}
			],
			"sid": 647690028442906,
			"effectTypes": [],
			"isInitiallyVisible": true,
			"color": [
				1,
				1,
				1,
				1
			],
			"backgroundColor": [
				0.3686274509803922,
				0.3686274509803922,
				0.3686274509803922,
				1
			],
			"isTransparent": false,
			"parallaxX": 1,
			"parallaxY": 1,
			"scaleRate": 1,
			"forceOwnTexture": false,
			"useRenderCells": false,
			"blendMode": "normal",
			"global": false
		}
	],
	"sid": 967776105208857,
	"nonworld-instances": [],
	"effectTypes": [],
	"width": 1440,
	"height": 1440,
	"unboundedScrolling": false,
	"eventSheet": null
}