{"propertiesBar":{"properties":[{"name":"About","expanded":true,"children":[]},{"name":"Colors","expanded":true,"children":[]},{"name":"Startup","expanded":true,"children":[]},{"name":"Display","expanded":true,"children":[{"name":"Viewport size","expanded":false,"children":[]}]},{"name":"Advanced","expanded":false,"children":[]},{"name":"Editor","expanded":true,"children":[]}],"scrollPosition":0},"openTabs":{"active":{"name":"eSetup","type":"eventSheet"},"open":[{"name":"Maze 1","type":"layout"},{"name":"eGame","type":"eventSheet"},{"name":"eTODO","type":"eventSheet"},{"name":"eSetup","type":"eventSheet"}]},"previewEffects":true,"previewBrowser":"default","pauseOnUnfocus":false,"projectBar":{"name":"<root>","children":[{"name":"Void Scavenge","expanded":true,"children":[{"name":"Layouts","expanded":true,"children":[{"name":"Maze 1","expanded":true,"children":[]}]},{"name":"Event sheets","expanded":true,"children":[{"name":"eGame","expanded":true,"children":[]},{"name":"eSetup","expanded":true,"children":[]},{"name":"eTODO","expanded":true,"children":[]}]},{"name":"Scripts","expanded":true,"children":[]},{"name":"Object types","expanded":true,"children":[{"name":"ActiveCellMarker","expanded":true,"children":[]},{"name":"Browser","expanded":true,"children":[]},{"name":"Item","expanded":true,"children":[]},{"name":"ItemPlace","expanded":true,"children":[]},{"name":"PlacedItems","expanded":true,"children":[]},{"name":"Player","expanded":true,"children":[]},{"name":"ShadowLight","expanded":true,"children":[]},{"name":"TiledBackground","expanded":true,"children":[]},{"name":"UIBackground","expanded":true,"children":[]},{"name":"Wall","expanded":true,"children":[]}]},{"name":"Families","expanded":true,"children":[]},{"name":"Timelines","expanded":true,"children":[{"name":"Eases","expanded":false,"children":[]}]},{"name":"Sounds","expanded":true,"children":[]},{"name":"Music","expanded":true,"children":[]},{"name":"Videos","expanded":true,"children":[]},{"name":"Fonts","expanded":true,"children":[]},{"name":"Icons","expanded":false,"children":[{"name":"icon-128.png","expanded":true,"children":[]},{"name":"icon-16.png","expanded":true,"children":[]},{"name":"icon-256.png","expanded":true,"children":[]},{"name":"icon-32.png","expanded":true,"children":[]},{"name":"icon-512.png","expanded":true,"children":[]},{"name":"icon-64.png","expanded":true,"children":[]},{"name":"loading-logo.png","expanded":true,"children":[]}]},{"name":"Files","expanded":true,"children":[]}]}]},"propertiesBarActiveObject":{"name":"instances","type":"array"}}