{
	"name": "TimeBar",
	"plugin-id": "Sprite",
	"sid": 995496322654142,
	"isGlobal": false,
	"instanceVariables": [],
	"behaviorTypes": [],
	"effectTypes": [],
	"animations": {
		"items": [
			{
				"frames": [
					{
						"width": 214,
						"height": 7,
						"originX": 0,
						"originY": 0,
						"originalSource": "",
						"exportFormat": "png",
						"exportQuality": 0.8,
						"imageSpriteId": 7671411,
						"collisionPoly": {
							"points": [
								0,
								0,
								0.5,
								0,
								0.9953271028037384,
								0,
								0.9953271028037384,
								0.5,
								0.9953271028037384,
								0.8571428571428571,
								0.5,
								0.8571428571428571,
								0,
								0.8571428571428571,
								0,
								0.5
							]
						},
						"useCollisionPoly": true,
						"duration": 1
					}
				],
				"sid": 532280417977795,
				"name": "Animation 1",
				"isLooping": false,
				"isPingPong": false,
				"repeatCount": 1,
				"repeatTo": 0,
				"speed": 5
			}
		],
		"subfolders": []
	}
}