{
	"name": "UIBorder",
	"plugin-id": "Sprite",
	"sid": 287580875864783,
	"isGlobal": false,
	"instanceVariables": [],
	"behaviorTypes": [],
	"effectTypes": [],
	"animations": {
		"items": [
			{
				"frames": [
					{
						"width": 640,
						"height": 480,
						"originX": 0.5,
						"originY": 0.5,
						"originalSource": "",
						"exportFormat": "png",
						"exportQuality": 0.8,
						"imageSpriteId": 2696013,
						"collisionPoly": {
							"points": [
								0,
								0,
								0.5,
								0,
								0.9984375,
								0,
								0.9984375,
								0.5,
								0.9984375,
								0.9979166666666667,
								0.5,
								0.9979166666666667,
								0,
								0.9979166666666667,
								0,
								0.5
							]
						},
						"useCollisionPoly": true,
						"duration": 1
					}
				],
				"sid": 651543663146739,
				"name": "Animation 1",
				"isLooping": false,
				"isPingPong": false,
				"repeatCount": 1,
				"repeatTo": 0,
				"speed": 5
			}
		],
		"subfolders": []
	}
}